Metadata-Version: 1.1
Name: LN0SCIs
Version: 0.1.0
Summary: Simultaneous CIs for Ratios of Means of Log-Normal Populations with Zeros
Home-page: https://dataxujing.github.io/
Author: Jing Xu, Xinmin Li, Hua Liang
Author-email: 274762204@qq.com
License: Apache License, Version 2.0
Platform: Linux/Windows
Classifier: Development Status :: 3 - Alpha
Classifier: Topic :: Text Processing
Classifier: License :: OSI Approved :: MIT License
Classifier: Programming Language :: Python :: 2
Classifier: Programming Language :: Python :: 2.7
Classifier: Programming Language :: Python :: 3
Classifier: Programming Language :: Python :: 3.5
